<?xml version="1.0" encoding="UTF-8"?>
<spirit:component xmlns:xilinx="http://www.xilinx.com" xmlns:spirit="http://www.spiritconsortium.org/XMLSchema/SPIRIT/1685-2009" xmlns:xsi="http://www.w3.org/2001/XMLSchema-instance">
  <spirit:vendor>ohio-state.edu</spirit:vendor>
  <spirit:library>user</spirit:library>
  <spirit:name>axi_ethernet_streamer</spirit:name>
  <spirit:version>1.0</spirit:version>
  <spirit:busInterfaces>
    <spirit:busInterface>
      <spirit:name>s_axis_eth_tx</spirit:name>
      <spirit:busType spirit:vendor="xilinx.com" spirit:library="interface" spirit:name="axis" spirit:version="1.0"/>
      <spirit:abstractionType spirit:vendor="xilinx.com" spirit:library="interface" spirit:name="axis_rtl" spirit:version="1.0"/>
      <spirit:slave/>
      <spirit:portMaps>
        <spirit:portMap>
          <spirit:logicalPort>
            <spirit:name>TDATA</spirit:name>
          </spirit:logicalPort>
          <spirit:physicalPort>
            <spirit:name>s_axis_eth_tx_tdata</spirit:name>
            <spirit:vector>
              <spirit:left spirit:format="long">7</spirit:left>
              <spirit:right spirit:format="long">0</spirit:right>
            </spirit:vector>
          </spirit:physicalPort>
        </spirit:portMap>
        <spirit:portMap>
          <spirit:logicalPort>
            <spirit:name>TLAST</spirit:name>
          </spirit:logicalPort>
          <spirit:physicalPort>
            <spirit:name>s_axis_eth_tx_tlast</spirit:name>
          </spirit:physicalPort>
        </spirit:portMap>
        <spirit:portMap>
          <spirit:logicalPort>
            <spirit:name>TVALID</spirit:name>
          </spirit:logicalPort>
          <spirit:physicalPort>
            <spirit:name>s_axis_eth_tx_tvalid</spirit:name>
          </spirit:physicalPort>
        </spirit:portMap>
        <spirit:portMap>
          <spirit:logicalPort>
            <spirit:name>TREADY</spirit:name>
          </spirit:logicalPort>
          <spirit:physicalPort>
            <spirit:name>s_axis_eth_tx_tready</spirit:name>
          </spirit:physicalPort>
        </spirit:portMap>
      </spirit:portMaps>
      <spirit:parameters>
        <spirit:parameter>
          <spirit:name>TDATA_NUM_BYTES</spirit:name>
          <spirit:value spirit:id="BUSIFPARAM_VALUE.S_AXIS_ETH_TX.TDATA_NUM_BYTES">1</spirit:value>
        </spirit:parameter>
        <spirit:parameter>
          <spirit:name>TDEST_WIDTH</spirit:name>
          <spirit:value spirit:id="BUSIFPARAM_VALUE.S_AXIS_ETH_TX.TDEST_WIDTH">0</spirit:value>
        </spirit:parameter>
        <spirit:parameter>
          <spirit:name>TID_WIDTH</spirit:name>
          <spirit:value spirit:id="BUSIFPARAM_VALUE.S_AXIS_ETH_TX.TID_WIDTH">0</spirit:value>
        </spirit:parameter>
        <spirit:parameter>
          <spirit:name>TUSER_WIDTH</spirit:name>
          <spirit:value spirit:id="BUSIFPARAM_VALUE.S_AXIS_ETH_TX.TUSER_WIDTH">0</spirit:value>
        </spirit:parameter>
        <spirit:parameter>
          <spirit:name>HAS_TREADY</spirit:name>
          <spirit:value spirit:id="BUSIFPARAM_VALUE.S_AXIS_ETH_TX.HAS_TREADY">1</spirit:value>
        </spirit:parameter>
        <spirit:parameter>
          <spirit:name>HAS_TSTRB</spirit:name>
          <spirit:value spirit:id="BUSIFPARAM_VALUE.S_AXIS_ETH_TX.HAS_TSTRB">0</spirit:value>
        </spirit:parameter>
        <spirit:parameter>
          <spirit:name>HAS_TKEEP</spirit:name>
          <spirit:value spirit:id="BUSIFPARAM_VALUE.S_AXIS_ETH_TX.HAS_TKEEP">0</spirit:value>
        </spirit:parameter>
        <spirit:parameter>
          <spirit:name>HAS_TLAST</spirit:name>
          <spirit:value spirit:id="BUSIFPARAM_VALUE.S_AXIS_ETH_TX.HAS_TLAST">1</spirit:value>
        </spirit:parameter>
        <spirit:parameter>
          <spirit:name>LAYERED_METADATA</spirit:name>
          <spirit:value spirit:id="BUSIFPARAM_VALUE.S_AXIS_ETH_TX.LAYERED_METADATA">undef</spirit:value>
        </spirit:parameter>
      </spirit:parameters>
    </spirit:busInterface>
    <spirit:busInterface>
      <spirit:name>m_axis_eth_rx</spirit:name>
      <spirit:busType spirit:vendor="xilinx.com" spirit:library="interface" spirit:name="axis" spirit:version="1.0"/>
      <spirit:abstractionType spirit:vendor="xilinx.com" spirit:library="interface" spirit:name="axis_rtl" spirit:version="1.0"/>
      <spirit:master/>
      <spirit:portMaps>
        <spirit:portMap>
          <spirit:logicalPort>
            <spirit:name>TDATA</spirit:name>
          </spirit:logicalPort>
          <spirit:physicalPort>
            <spirit:name>m_axis_eth_rx_tdata</spirit:name>
            <spirit:vector>
              <spirit:left spirit:format="long">7</spirit:left>
              <spirit:right spirit:format="long">0</spirit:right>
            </spirit:vector>
          </spirit:physicalPort>
        </spirit:portMap>
        <spirit:portMap>
          <spirit:logicalPort>
            <spirit:name>TKEEP</spirit:name>
          </spirit:logicalPort>
          <spirit:physicalPort>
            <spirit:name>m_axis_eth_rx_tkeep</spirit:name>
          </spirit:physicalPort>
        </spirit:portMap>
        <spirit:portMap>
          <spirit:logicalPort>
            <spirit:name>TLAST</spirit:name>
          </spirit:logicalPort>
          <spirit:physicalPort>
            <spirit:name>m_axis_eth_rx_tlast</spirit:name>
          </spirit:physicalPort>
        </spirit:portMap>
        <spirit:portMap>
          <spirit:logicalPort>
            <spirit:name>TREADY</spirit:name>
          </spirit:logicalPort>
          <spirit:physicalPort>
            <spirit:name>m_axis_eth_rx_tready</spirit:name>
          </spirit:physicalPort>
        </spirit:portMap>
        <spirit:portMap>
          <spirit:logicalPort>
            <spirit:name>TVALID</spirit:name>
          </spirit:logicalPort>
          <spirit:physicalPort>
            <spirit:name>m_axis_eth_rx_tvalid</spirit:name>
          </spirit:physicalPort>
        </spirit:portMap>
      </spirit:portMaps>
      <spirit:parameters>
        <spirit:parameter>
          <spirit:name>TDATA_NUM_BYTES</spirit:name>
          <spirit:value spirit:id="BUSIFPARAM_VALUE.M_AXIS_ETH_RX.TDATA_NUM_BYTES">1</spirit:value>
        </spirit:parameter>
        <spirit:parameter>
          <spirit:name>TDEST_WIDTH</spirit:name>
          <spirit:value spirit:id="BUSIFPARAM_VALUE.M_AXIS_ETH_RX.TDEST_WIDTH">0</spirit:value>
        </spirit:parameter>
        <spirit:parameter>
          <spirit:name>TID_WIDTH</spirit:name>
          <spirit:value spirit:id="BUSIFPARAM_VALUE.M_AXIS_ETH_RX.TID_WIDTH">0</spirit:value>
        </spirit:parameter>
        <spirit:parameter>
          <spirit:name>TUSER_WIDTH</spirit:name>
          <spirit:value spirit:id="BUSIFPARAM_VALUE.M_AXIS_ETH_RX.TUSER_WIDTH">0</spirit:value>
        </spirit:parameter>
        <spirit:parameter>
          <spirit:name>HAS_TREADY</spirit:name>
          <spirit:value spirit:id="BUSIFPARAM_VALUE.M_AXIS_ETH_RX.HAS_TREADY">1</spirit:value>
        </spirit:parameter>
        <spirit:parameter>
          <spirit:name>HAS_TSTRB</spirit:name>
          <spirit:value spirit:id="BUSIFPARAM_VALUE.M_AXIS_ETH_RX.HAS_TSTRB">0</spirit:value>
        </spirit:parameter>
        <spirit:parameter>
          <spirit:name>HAS_TKEEP</spirit:name>
          <spirit:value spirit:id="BUSIFPARAM_VALUE.M_AXIS_ETH_RX.HAS_TKEEP">1</spirit:value>
        </spirit:parameter>
        <spirit:parameter>
          <spirit:name>HAS_TLAST</spirit:name>
          <spirit:value spirit:id="BUSIFPARAM_VALUE.M_AXIS_ETH_RX.HAS_TLAST">1</spirit:value>
        </spirit:parameter>
        <spirit:parameter>
          <spirit:name>LAYERED_METADATA</spirit:name>
          <spirit:value spirit:id="BUSIFPARAM_VALUE.M_AXIS_ETH_RX.LAYERED_METADATA">undef</spirit:value>
        </spirit:parameter>
      </spirit:parameters>
    </spirit:busInterface>
    <spirit:busInterface>
      <spirit:name>mii</spirit:name>
      <spirit:busType spirit:vendor="xilinx.com" spirit:library="interface" spirit:name="mii" spirit:version="1.0"/>
      <spirit:abstractionType spirit:vendor="xilinx.com" spirit:library="interface" spirit:name="mii_rtl" spirit:version="1.0"/>
      <spirit:master/>
      <spirit:portMaps>
        <spirit:portMap>
          <spirit:logicalPort>
            <spirit:name>COL</spirit:name>
          </spirit:logicalPort>
          <spirit:physicalPort>
            <spirit:name>mii_col</spirit:name>
          </spirit:physicalPort>
        </spirit:portMap>
        <spirit:portMap>
          <spirit:logicalPort>
            <spirit:name>CRS</spirit:name>
          </spirit:logicalPort>
          <spirit:physicalPort>
            <spirit:name>mii_crs</spirit:name>
          </spirit:physicalPort>
        </spirit:portMap>
        <spirit:portMap>
          <spirit:logicalPort>
            <spirit:name>RST_N</spirit:name>
          </spirit:logicalPort>
          <spirit:physicalPort>
            <spirit:name>mii_rst_n</spirit:name>
          </spirit:physicalPort>
        </spirit:portMap>
        <spirit:portMap>
          <spirit:logicalPort>
            <spirit:name>RX_CLK</spirit:name>
          </spirit:logicalPort>
          <spirit:physicalPort>
            <spirit:name>mii_rx_clk</spirit:name>
          </spirit:physicalPort>
        </spirit:portMap>
        <spirit:portMap>
          <spirit:logicalPort>
            <spirit:name>RX_DV</spirit:name>
          </spirit:logicalPort>
          <spirit:physicalPort>
            <spirit:name>mii_rx_dv</spirit:name>
          </spirit:physicalPort>
        </spirit:portMap>
        <spirit:portMap>
          <spirit:logicalPort>
            <spirit:name>RX_ER</spirit:name>
          </spirit:logicalPort>
          <spirit:physicalPort>
            <spirit:name>mii_rx_er</spirit:name>
          </spirit:physicalPort>
        </spirit:portMap>
        <spirit:portMap>
          <spirit:logicalPort>
            <spirit:name>RXD</spirit:name>
          </spirit:logicalPort>
          <spirit:physicalPort>
            <spirit:name>mii_rxd</spirit:name>
            <spirit:vector>
              <spirit:left spirit:format="long">3</spirit:left>
              <spirit:right spirit:format="long">0</spirit:right>
            </spirit:vector>
          </spirit:physicalPort>
        </spirit:portMap>
        <spirit:portMap>
          <spirit:logicalPort>
            <spirit:name>TX_CLK</spirit:name>
          </spirit:logicalPort>
          <spirit:physicalPort>
            <spirit:name>mii_tx_clk</spirit:name>
          </spirit:physicalPort>
        </spirit:portMap>
        <spirit:portMap>
          <spirit:logicalPort>
            <spirit:name>TX_EN</spirit:name>
          </spirit:logicalPort>
          <spirit:physicalPort>
            <spirit:name>mii_tx_en</spirit:name>
          </spirit:physicalPort>
        </spirit:portMap>
        <spirit:portMap>
          <spirit:logicalPort>
            <spirit:name>TXD</spirit:name>
          </spirit:logicalPort>
          <spirit:physicalPort>
            <spirit:name>mii_txd</spirit:name>
            <spirit:vector>
              <spirit:left spirit:format="long">3</spirit:left>
              <spirit:right spirit:format="long">0</spirit:right>
            </spirit:vector>
          </spirit:physicalPort>
        </spirit:portMap>
      </spirit:portMaps>
      <spirit:parameters>
        <spirit:parameter>
          <spirit:name>BUSIF.BOARD_INTERFACE</spirit:name>
          <spirit:value spirit:id="BUSIFPARAM_VALUE.MII.BUSIF.BOARD_INTERFACE">Custom</spirit:value>
        </spirit:parameter>
      </spirit:parameters>
    </spirit:busInterface>
    <spirit:busInterface>
      <spirit:name>mdio</spirit:name>
      <spirit:busType spirit:vendor="xilinx.com" spirit:library="interface" spirit:name="mdio" spirit:version="1.0"/>
      <spirit:abstractionType spirit:vendor="xilinx.com" spirit:library="interface" spirit:name="mdio_rtl" spirit:version="1.0"/>
      <spirit:master/>
      <spirit:portMaps>
        <spirit:portMap>
          <spirit:logicalPort>
            <spirit:name>MDC</spirit:name>
          </spirit:logicalPort>
          <spirit:physicalPort>
            <spirit:name>mdio_mdc</spirit:name>
          </spirit:physicalPort>
        </spirit:portMap>
        <spirit:portMap>
          <spirit:logicalPort>
            <spirit:name>MDIO_I</spirit:name>
          </spirit:logicalPort>
          <spirit:physicalPort>
            <spirit:name>mdio_mdio_i</spirit:name>
          </spirit:physicalPort>
        </spirit:portMap>
        <spirit:portMap>
          <spirit:logicalPort>
            <spirit:name>MDIO_O</spirit:name>
          </spirit:logicalPort>
          <spirit:physicalPort>
            <spirit:name>mdio_mdio_o</spirit:name>
          </spirit:physicalPort>
        </spirit:portMap>
        <spirit:portMap>
          <spirit:logicalPort>
            <spirit:name>MDIO_T</spirit:name>
          </spirit:logicalPort>
          <spirit:physicalPort>
            <spirit:name>mdio_mdio_t</spirit:name>
          </spirit:physicalPort>
        </spirit:portMap>
      </spirit:portMaps>
      <spirit:parameters>
        <spirit:parameter>
          <spirit:name>BUSIF.BOARD_INTERFACE</spirit:name>
          <spirit:value spirit:id="BUSIFPARAM_VALUE.MDIO.BUSIF.BOARD_INTERFACE">Custom</spirit:value>
        </spirit:parameter>
      </spirit:parameters>
    </spirit:busInterface>
    <spirit:busInterface>
      <spirit:name>CLK.CLK100</spirit:name>
      <spirit:busType spirit:vendor="xilinx.com" spirit:library="signal" spirit:name="clock" spirit:version="1.0"/>
      <spirit:abstractionType spirit:vendor="xilinx.com" spirit:library="signal" spirit:name="clock_rtl" spirit:version="1.0"/>
      <spirit:slave/>
      <spirit:portMaps>
        <spirit:portMap>
          <spirit:logicalPort>
            <spirit:name>CLK</spirit:name>
          </spirit:logicalPort>
          <spirit:physicalPort>
            <spirit:name>clk100</spirit:name>
          </spirit:physicalPort>
        </spirit:portMap>
      </spirit:portMaps>
      <spirit:parameters>
        <spirit:parameter>
          <spirit:name>FREQ_HZ</spirit:name>
          <spirit:value spirit:id="BUSIFPARAM_VALUE.CLK.CLK100.FREQ_HZ">100000000</spirit:value>
        </spirit:parameter>
        <spirit:parameter>
          <spirit:name>PHASE</spirit:name>
          <spirit:value spirit:id="BUSIFPARAM_VALUE.CLK.CLK100.PHASE">0.000</spirit:value>
        </spirit:parameter>
        <spirit:parameter>
          <spirit:name>ASSOCIATED_BUSIF</spirit:name>
          <spirit:value spirit:id="BUSIFPARAM_VALUE.CLK.CLK100.ASSOCIATED_BUSIF">m_axis_eth_rx</spirit:value>
        </spirit:parameter>
      </spirit:parameters>
    </spirit:busInterface>
    <spirit:busInterface>
      <spirit:name>RST.RESETN</spirit:name>
      <spirit:busType spirit:vendor="xilinx.com" spirit:library="signal" spirit:name="reset" spirit:version="1.0"/>
      <spirit:abstractionType spirit:vendor="xilinx.com" spirit:library="signal" spirit:name="reset_rtl" spirit:version="1.0"/>
      <spirit:slave/>
      <spirit:portMaps>
        <spirit:portMap>
          <spirit:logicalPort>
            <spirit:name>RST</spirit:name>
          </spirit:logicalPort>
          <spirit:physicalPort>
            <spirit:name>resetn</spirit:name>
          </spirit:physicalPort>
        </spirit:portMap>
      </spirit:portMaps>
      <spirit:parameters>
        <spirit:parameter>
          <spirit:name>POLARITY</spirit:name>
          <spirit:value spirit:id="BUSIFPARAM_VALUE.RST.RESETN.POLARITY">ACTIVE_LOW</spirit:value>
        </spirit:parameter>
      </spirit:parameters>
    </spirit:busInterface>
    <spirit:busInterface>
      <spirit:name>RST.RESET_OUT</spirit:name>
      <spirit:busType spirit:vendor="xilinx.com" spirit:library="signal" spirit:name="reset" spirit:version="1.0"/>
      <spirit:abstractionType spirit:vendor="xilinx.com" spirit:library="signal" spirit:name="reset_rtl" spirit:version="1.0"/>
      <spirit:master/>
      <spirit:portMaps>
        <spirit:portMap>
          <spirit:logicalPort>
            <spirit:name>RST</spirit:name>
          </spirit:logicalPort>
          <spirit:physicalPort>
            <spirit:name>reset_out</spirit:name>
          </spirit:physicalPort>
        </spirit:portMap>
      </spirit:portMaps>
      <spirit:parameters>
        <spirit:parameter>
          <spirit:name>POLARITY</spirit:name>
          <spirit:value spirit:id="BUSIFPARAM_VALUE.RST.RESET_OUT.POLARITY">ACTIVE_HIGH</spirit:value>
        </spirit:parameter>
      </spirit:parameters>
    </spirit:busInterface>
  </spirit:busInterfaces>
  <spirit:model>
    <spirit:views>
      <spirit:view>
        <spirit:name>xilinx_anylanguagesynthesis</spirit:name>
        <spirit:displayName>Synthesis</spirit:displayName>
        <spirit:envIdentifier>:vivado.xilinx.com:synthesis</spirit:envIdentifier>
        <spirit:language>Verilog</spirit:language>
        <spirit:modelName>axi_ethernet_streamer</spirit:modelName>
        <spirit:fileSetRef>
          <spirit:localName>xilinx_anylanguagesynthesis_ohio_state_edu_user_picoblaze_ethernet_lite_controller_1_0__ref_view_fileset</spirit:localName>
        </spirit:fileSetRef>
        <spirit:fileSetRef>
          <spirit:localName>xilinx_anylanguagesynthesis_xilinx_com_ip_axi_datamover_5_1__ref_view_fileset</spirit:localName>
        </spirit:fileSetRef>
        <spirit:fileSetRef>
          <spirit:localName>xilinx_anylanguagesynthesis_xilinx_com_ip_axi_protocol_converter_2_1__ref_view_fileset</spirit:localName>
        </spirit:fileSetRef>
        <spirit:fileSetRef>
          <spirit:localName>xilinx_anylanguagesynthesis_xilinx_com_ip_axi_ethernetlite_3_0__ref_view_fileset</spirit:localName>
        </spirit:fileSetRef>
        <spirit:fileSetRef>
          <spirit:localName>xilinx_anylanguagesynthesis_xilinx_com_ip_xlconstant_1_1__ref_view_fileset</spirit:localName>
        </spirit:fileSetRef>
        <spirit:fileSetRef>
          <spirit:localName>xilinx_anylanguagesynthesis_xilinx_com_ip_proc_sys_reset_5_0__ref_view_fileset</spirit:localName>
        </spirit:fileSetRef>
        <spirit:fileSetRef>
          <spirit:localName>xilinx_anylanguagesynthesis_xilinx_com_ip_axi_crossbar_2_1__ref_view_fileset</spirit:localName>
        </spirit:fileSetRef>
        <spirit:fileSetRef>
          <spirit:localName>xilinx_anylanguagesynthesis_xilinx_com_ip_system_ila_1_0__ref_view_fileset</spirit:localName>
        </spirit:fileSetRef>
        <spirit:fileSetRef>
          <spirit:localName>xilinx_anylanguagesynthesis_view_fileset</spirit:localName>
        </spirit:fileSetRef>
        <spirit:parameters>
          <spirit:parameter>
            <spirit:name>viewChecksum</spirit:name>
            <spirit:value>18c891e5</spirit:value>
          </spirit:parameter>
        </spirit:parameters>
      </spirit:view>
      <spirit:view>
        <spirit:name>xilinx_anylanguagebehavioralsimulation</spirit:name>
        <spirit:displayName>Simulation</spirit:displayName>
        <spirit:envIdentifier>:vivado.xilinx.com:simulation</spirit:envIdentifier>
        <spirit:language>Verilog</spirit:language>
        <spirit:modelName>axi_ethernet_streamer</spirit:modelName>
        <spirit:fileSetRef>
          <spirit:localName>xilinx_anylanguagebehavioralsimulation_ohio_state_edu_user_picoblaze_ethernet_lite_controller_1_0__ref_view_fileset</spirit:localName>
        </spirit:fileSetRef>
        <spirit:fileSetRef>
          <spirit:localName>xilinx_anylanguagebehavioralsimulation_xilinx_com_ip_axi_datamover_5_1__ref_view_fileset</spirit:localName>
        </spirit:fileSetRef>
        <spirit:fileSetRef>
          <spirit:localName>xilinx_anylanguagebehavioralsimulation_xilinx_com_ip_axi_protocol_converter_2_1__ref_view_fileset</spirit:localName>
        </spirit:fileSetRef>
        <spirit:fileSetRef>
          <spirit:localName>xilinx_anylanguagebehavioralsimulation_xilinx_com_ip_axi_ethernetlite_3_0__ref_view_fileset</spirit:localName>
        </spirit:fileSetRef>
        <spirit:fileSetRef>
          <spirit:localName>xilinx_anylanguagebehavioralsimulation_xilinx_com_ip_xlconstant_1_1__ref_view_fileset</spirit:localName>
        </spirit:fileSetRef>
        <spirit:fileSetRef>
          <spirit:localName>xilinx_anylanguagebehavioralsimulation_xilinx_com_ip_proc_sys_reset_5_0__ref_view_fileset</spirit:localName>
        </spirit:fileSetRef>
        <spirit:fileSetRef>
          <spirit:localName>xilinx_anylanguagebehavioralsimulation_xilinx_com_ip_axi_crossbar_2_1__ref_view_fileset</spirit:localName>
        </spirit:fileSetRef>
        <spirit:fileSetRef>
          <spirit:localName>xilinx_anylanguagebehavioralsimulation_xilinx_com_ip_system_ila_1_0__ref_view_fileset</spirit:localName>
        </spirit:fileSetRef>
        <spirit:fileSetRef>
          <spirit:localName>xilinx_anylanguagebehavioralsimulation_view_fileset</spirit:localName>
        </spirit:fileSetRef>
        <spirit:parameters>
          <spirit:parameter>
            <spirit:name>viewChecksum</spirit:name>
            <spirit:value>aaf0c652</spirit:value>
          </spirit:parameter>
        </spirit:parameters>
      </spirit:view>
      <spirit:view>
        <spirit:name>xilinx_xpgui</spirit:name>
        <spirit:displayName>UI Layout</spirit:displayName>
        <spirit:envIdentifier>:vivado.xilinx.com:xgui.ui</spirit:envIdentifier>
        <spirit:fileSetRef>
          <spirit:localName>xilinx_xpgui_view_fileset</spirit:localName>
        </spirit:fileSetRef>
        <spirit:parameters>
          <spirit:parameter>
            <spirit:name>viewChecksum</spirit:name>
            <spirit:value>f64a5dae</spirit:value>
          </spirit:parameter>
        </spirit:parameters>
      </spirit:view>
    </spirit:views>
    <spirit:ports>
      <spirit:port>
        <spirit:name>clk100</spirit:name>
        <spirit:wire>
          <spirit:direction>in</spirit:direction>
          <spirit:wireTypeDefs>
            <spirit:wireTypeDef>
              <spirit:typeName>std_logic</spirit:typeName>
              <spirit:viewNameRef>xilinx_anylanguagesynthesis</spirit:viewNameRef>
              <spirit:viewNameRef>xilinx_anylanguagebehavioralsimulation</spirit:viewNameRef>
            </spirit:wireTypeDef>
          </spirit:wireTypeDefs>
        </spirit:wire>
      </spirit:port>
      <spirit:port>
        <spirit:name>locked</spirit:name>
        <spirit:wire>
          <spirit:direction>in</spirit:direction>
          <spirit:wireTypeDefs>
            <spirit:wireTypeDef>
              <spirit:typeName>std_logic</spirit:typeName>
              <spirit:viewNameRef>xilinx_anylanguagesynthesis</spirit:viewNameRef>
              <spirit:viewNameRef>xilinx_anylanguagebehavioralsimulation</spirit:viewNameRef>
            </spirit:wireTypeDef>
          </spirit:wireTypeDefs>
        </spirit:wire>
      </spirit:port>
      <spirit:port>
        <spirit:name>m_axis_eth_rx_tdata</spirit:name>
        <spirit:wire>
          <spirit:direction>out</spirit:direction>
          <spirit:vector>
            <spirit:left spirit:format="long">7</spirit:left>
            <spirit:right spirit:format="long">0</spirit:right>
          </spirit:vector>
          <spirit:wireTypeDefs>
            <spirit:wireTypeDef>
              <spirit:typeName>std_logic_vector</spirit:typeName>
              <spirit:viewNameRef>xilinx_anylanguagesynthesis</spirit:viewNameRef>
              <spirit:viewNameRef>xilinx_anylanguagebehavioralsimulation</spirit:viewNameRef>
            </spirit:wireTypeDef>
          </spirit:wireTypeDefs>
        </spirit:wire>
      </spirit:port>
      <spirit:port>
        <spirit:name>m_axis_eth_rx_tkeep</spirit:name>
        <spirit:wire>
          <spirit:direction>out</spirit:direction>
          <spirit:vector>
            <spirit:left spirit:format="long">0</spirit:left>
            <spirit:right spirit:format="long">0</spirit:right>
          </spirit:vector>
          <spirit:wireTypeDefs>
            <spirit:wireTypeDef>
              <spirit:typeName>std_logic_vector</spirit:typeName>
              <spirit:viewNameRef>xilinx_anylanguagesynthesis</spirit:viewNameRef>
              <spirit:viewNameRef>xilinx_anylanguagebehavioralsimulation</spirit:viewNameRef>
            </spirit:wireTypeDef>
          </spirit:wireTypeDefs>
        </spirit:wire>
      </spirit:port>
      <spirit:port>
        <spirit:name>m_axis_eth_rx_tlast</spirit:name>
        <spirit:wire>
          <spirit:direction>out</spirit:direction>
          <spirit:wireTypeDefs>
            <spirit:wireTypeDef>
              <spirit:typeName>std_logic</spirit:typeName>
              <spirit:viewNameRef>xilinx_anylanguagesynthesis</spirit:viewNameRef>
              <spirit:viewNameRef>xilinx_anylanguagebehavioralsimulation</spirit:viewNameRef>
            </spirit:wireTypeDef>
          </spirit:wireTypeDefs>
        </spirit:wire>
      </spirit:port>
      <spirit:port>
        <spirit:name>m_axis_eth_rx_tready</spirit:name>
        <spirit:wire>
          <spirit:direction>in</spirit:direction>
          <spirit:wireTypeDefs>
            <spirit:wireTypeDef>
              <spirit:typeName>std_logic</spirit:typeName>
              <spirit:viewNameRef>xilinx_anylanguagesynthesis</spirit:viewNameRef>
              <spirit:viewNameRef>xilinx_anylanguagebehavioralsimulation</spirit:viewNameRef>
            </spirit:wireTypeDef>
          </spirit:wireTypeDefs>
        </spirit:wire>
      </spirit:port>
      <spirit:port>
        <spirit:name>m_axis_eth_rx_tvalid</spirit:name>
        <spirit:wire>
          <spirit:direction>out</spirit:direction>
          <spirit:wireTypeDefs>
            <spirit:wireTypeDef>
              <spirit:typeName>std_logic</spirit:typeName>
              <spirit:viewNameRef>xilinx_anylanguagesynthesis</spirit:viewNameRef>
              <spirit:viewNameRef>xilinx_anylanguagebehavioralsimulation</spirit:viewNameRef>
            </spirit:wireTypeDef>
          </spirit:wireTypeDefs>
        </spirit:wire>
      </spirit:port>
      <spirit:port>
        <spirit:name>mac_address</spirit:name>
        <spirit:wire>
          <spirit:direction>in</spirit:direction>
          <spirit:vector>
            <spirit:left spirit:format="long">47</spirit:left>
            <spirit:right spirit:format="long">0</spirit:right>
          </spirit:vector>
          <spirit:wireTypeDefs>
            <spirit:wireTypeDef>
              <spirit:typeName>std_logic_vector</spirit:typeName>
              <spirit:viewNameRef>xilinx_anylanguagesynthesis</spirit:viewNameRef>
              <spirit:viewNameRef>xilinx_anylanguagebehavioralsimulation</spirit:viewNameRef>
            </spirit:wireTypeDef>
          </spirit:wireTypeDefs>
        </spirit:wire>
      </spirit:port>
      <spirit:port>
        <spirit:name>mdio_mdc</spirit:name>
        <spirit:wire>
          <spirit:direction>out</spirit:direction>
          <spirit:wireTypeDefs>
            <spirit:wireTypeDef>
              <spirit:typeName>std_logic</spirit:typeName>
              <spirit:viewNameRef>xilinx_anylanguagesynthesis</spirit:viewNameRef>
              <spirit:viewNameRef>xilinx_anylanguagebehavioralsimulation</spirit:viewNameRef>
            </spirit:wireTypeDef>
          </spirit:wireTypeDefs>
        </spirit:wire>
      </spirit:port>
      <spirit:port>
        <spirit:name>mdio_mdio_i</spirit:name>
        <spirit:wire>
          <spirit:direction>in</spirit:direction>
          <spirit:wireTypeDefs>
            <spirit:wireTypeDef>
              <spirit:typeName>std_logic</spirit:typeName>
              <spirit:viewNameRef>xilinx_anylanguagesynthesis</spirit:viewNameRef>
              <spirit:viewNameRef>xilinx_anylanguagebehavioralsimulation</spirit:viewNameRef>
            </spirit:wireTypeDef>
          </spirit:wireTypeDefs>
        </spirit:wire>
      </spirit:port>
      <spirit:port>
        <spirit:name>mdio_mdio_o</spirit:name>
        <spirit:wire>
          <spirit:direction>out</spirit:direction>
          <spirit:wireTypeDefs>
            <spirit:wireTypeDef>
              <spirit:typeName>std_logic</spirit:typeName>
              <spirit:viewNameRef>xilinx_anylanguagesynthesis</spirit:viewNameRef>
              <spirit:viewNameRef>xilinx_anylanguagebehavioralsimulation</spirit:viewNameRef>
            </spirit:wireTypeDef>
          </spirit:wireTypeDefs>
        </spirit:wire>
      </spirit:port>
      <spirit:port>
        <spirit:name>mdio_mdio_t</spirit:name>
        <spirit:wire>
          <spirit:direction>out</spirit:direction>
          <spirit:wireTypeDefs>
            <spirit:wireTypeDef>
              <spirit:typeName>std_logic</spirit:typeName>
              <spirit:viewNameRef>xilinx_anylanguagesynthesis</spirit:viewNameRef>
              <spirit:viewNameRef>xilinx_anylanguagebehavioralsimulation</spirit:viewNameRef>
            </spirit:wireTypeDef>
          </spirit:wireTypeDefs>
        </spirit:wire>
      </spirit:port>
      <spirit:port>
        <spirit:name>mii_col</spirit:name>
        <spirit:wire>
          <spirit:direction>in</spirit:direction>
          <spirit:wireTypeDefs>
            <spirit:wireTypeDef>
              <spirit:typeName>std_logic</spirit:typeName>
              <spirit:viewNameRef>xilinx_anylanguagesynthesis</spirit:viewNameRef>
              <spirit:viewNameRef>xilinx_anylanguagebehavioralsimulation</spirit:viewNameRef>
            </spirit:wireTypeDef>
          </spirit:wireTypeDefs>
        </spirit:wire>
      </spirit:port>
      <spirit:port>
        <spirit:name>mii_crs</spirit:name>
        <spirit:wire>
          <spirit:direction>in</spirit:direction>
          <spirit:wireTypeDefs>
            <spirit:wireTypeDef>
              <spirit:typeName>std_logic</spirit:typeName>
              <spirit:viewNameRef>xilinx_anylanguagesynthesis</spirit:viewNameRef>
              <spirit:viewNameRef>xilinx_anylanguagebehavioralsimulation</spirit:viewNameRef>
            </spirit:wireTypeDef>
          </spirit:wireTypeDefs>
        </spirit:wire>
      </spirit:port>
      <spirit:port>
        <spirit:name>mii_rst_n</spirit:name>
        <spirit:wire>
          <spirit:direction>out</spirit:direction>
          <spirit:wireTypeDefs>
            <spirit:wireTypeDef>
              <spirit:typeName>std_logic</spirit:typeName>
              <spirit:viewNameRef>xilinx_anylanguagesynthesis</spirit:viewNameRef>
              <spirit:viewNameRef>xilinx_anylanguagebehavioralsimulation</spirit:viewNameRef>
            </spirit:wireTypeDef>
          </spirit:wireTypeDefs>
        </spirit:wire>
      </spirit:port>
      <spirit:port>
        <spirit:name>mii_rx_clk</spirit:name>
        <spirit:wire>
          <spirit:direction>in</spirit:direction>
          <spirit:wireTypeDefs>
            <spirit:wireTypeDef>
              <spirit:typeName>std_logic</spirit:typeName>
              <spirit:viewNameRef>xilinx_anylanguagesynthesis</spirit:viewNameRef>
              <spirit:viewNameRef>xilinx_anylanguagebehavioralsimulation</spirit:viewNameRef>
            </spirit:wireTypeDef>
          </spirit:wireTypeDefs>
        </spirit:wire>
      </spirit:port>
      <spirit:port>
        <spirit:name>mii_rx_dv</spirit:name>
        <spirit:wire>
          <spirit:direction>in</spirit:direction>
          <spirit:wireTypeDefs>
            <spirit:wireTypeDef>
              <spirit:typeName>std_logic</spirit:typeName>
              <spirit:viewNameRef>xilinx_anylanguagesynthesis</spirit:viewNameRef>
              <spirit:viewNameRef>xilinx_anylanguagebehavioralsimulation</spirit:viewNameRef>
            </spirit:wireTypeDef>
          </spirit:wireTypeDefs>
        </spirit:wire>
      </spirit:port>
      <spirit:port>
        <spirit:name>mii_rx_er</spirit:name>
        <spirit:wire>
          <spirit:direction>in</spirit:direction>
          <spirit:wireTypeDefs>
            <spirit:wireTypeDef>
              <spirit:typeName>std_logic</spirit:typeName>
              <spirit:viewNameRef>xilinx_anylanguagesynthesis</spirit:viewNameRef>
              <spirit:viewNameRef>xilinx_anylanguagebehavioralsimulation</spirit:viewNameRef>
            </spirit:wireTypeDef>
          </spirit:wireTypeDefs>
        </spirit:wire>
      </spirit:port>
      <spirit:port>
        <spirit:name>mii_rxd</spirit:name>
        <spirit:wire>
          <spirit:direction>in</spirit:direction>
          <spirit:vector>
            <spirit:left spirit:format="long">3</spirit:left>
            <spirit:right spirit:format="long">0</spirit:right>
          </spirit:vector>
          <spirit:wireTypeDefs>
            <spirit:wireTypeDef>
              <spirit:typeName>std_logic_vector</spirit:typeName>
              <spirit:viewNameRef>xilinx_anylanguagesynthesis</spirit:viewNameRef>
              <spirit:viewNameRef>xilinx_anylanguagebehavioralsimulation</spirit:viewNameRef>
            </spirit:wireTypeDef>
          </spirit:wireTypeDefs>
        </spirit:wire>
      </spirit:port>
      <spirit:port>
        <spirit:name>mii_tx_clk</spirit:name>
        <spirit:wire>
          <spirit:direction>in</spirit:direction>
          <spirit:wireTypeDefs>
            <spirit:wireTypeDef>
              <spirit:typeName>std_logic</spirit:typeName>
              <spirit:viewNameRef>xilinx_anylanguagesynthesis</spirit:viewNameRef>
              <spirit:viewNameRef>xilinx_anylanguagebehavioralsimulation</spirit:viewNameRef>
            </spirit:wireTypeDef>
          </spirit:wireTypeDefs>
        </spirit:wire>
      </spirit:port>
      <spirit:port>
        <spirit:name>mii_tx_en</spirit:name>
        <spirit:wire>
          <spirit:direction>out</spirit:direction>
          <spirit:wireTypeDefs>
            <spirit:wireTypeDef>
              <spirit:typeName>std_logic</spirit:typeName>
              <spirit:viewNameRef>xilinx_anylanguagesynthesis</spirit:viewNameRef>
              <spirit:viewNameRef>xilinx_anylanguagebehavioralsimulation</spirit:viewNameRef>
            </spirit:wireTypeDef>
          </spirit:wireTypeDefs>
        </spirit:wire>
      </spirit:port>
      <spirit:port>
        <spirit:name>mii_txd</spirit:name>
        <spirit:wire>
          <spirit:direction>out</spirit:direction>
          <spirit:vector>
            <spirit:left spirit:format="long">3</spirit:left>
            <spirit:right spirit:format="long">0</spirit:right>
          </spirit:vector>
          <spirit:wireTypeDefs>
            <spirit:wireTypeDef>
              <spirit:typeName>std_logic_vector</spirit:typeName>
              <spirit:viewNameRef>xilinx_anylanguagesynthesis</spirit:viewNameRef>
              <spirit:viewNameRef>xilinx_anylanguagebehavioralsimulation</spirit:viewNameRef>
            </spirit:wireTypeDef>
          </spirit:wireTypeDefs>
        </spirit:wire>
      </spirit:port>
      <spirit:port>
        <spirit:name>reset_out</spirit:name>
        <spirit:wire>
          <spirit:direction>out</spirit:direction>
          <spirit:vector>
            <spirit:left spirit:format="long">0</spirit:left>
            <spirit:right spirit:format="long">0</spirit:right>
          </spirit:vector>
          <spirit:wireTypeDefs>
            <spirit:wireTypeDef>
              <spirit:typeName>std_logic_vector</spirit:typeName>
              <spirit:viewNameRef>xilinx_anylanguagesynthesis</spirit:viewNameRef>
              <spirit:viewNameRef>xilinx_anylanguagebehavioralsimulation</spirit:viewNameRef>
            </spirit:wireTypeDef>
          </spirit:wireTypeDefs>
        </spirit:wire>
      </spirit:port>
      <spirit:port>
        <spirit:name>resetn</spirit:name>
        <spirit:wire>
          <spirit:direction>in</spirit:direction>
          <spirit:wireTypeDefs>
            <spirit:wireTypeDef>
              <spirit:typeName>std_logic</spirit:typeName>
              <spirit:viewNameRef>xilinx_anylanguagesynthesis</spirit:viewNameRef>
              <spirit:viewNameRef>xilinx_anylanguagebehavioralsimulation</spirit:viewNameRef>
            </spirit:wireTypeDef>
          </spirit:wireTypeDefs>
        </spirit:wire>
      </spirit:port>
      <spirit:port>
        <spirit:name>s_axis_eth_tx_tdata</spirit:name>
        <spirit:wire>
          <spirit:direction>in</spirit:direction>
          <spirit:vector>
            <spirit:left spirit:format="long">7</spirit:left>
            <spirit:right spirit:format="long">0</spirit:right>
          </spirit:vector>
          <spirit:wireTypeDefs>
            <spirit:wireTypeDef>
              <spirit:typeName>std_logic_vector</spirit:typeName>
              <spirit:viewNameRef>xilinx_anylanguagesynthesis</spirit:viewNameRef>
              <spirit:viewNameRef>xilinx_anylanguagebehavioralsimulation</spirit:viewNameRef>
            </spirit:wireTypeDef>
          </spirit:wireTypeDefs>
        </spirit:wire>
      </spirit:port>
      <spirit:port>
        <spirit:name>s_axis_eth_tx_tlast</spirit:name>
        <spirit:wire>
          <spirit:direction>in</spirit:direction>
          <spirit:wireTypeDefs>
            <spirit:wireTypeDef>
              <spirit:typeName>std_logic</spirit:typeName>
              <spirit:viewNameRef>xilinx_anylanguagesynthesis</spirit:viewNameRef>
              <spirit:viewNameRef>xilinx_anylanguagebehavioralsimulation</spirit:viewNameRef>
            </spirit:wireTypeDef>
          </spirit:wireTypeDefs>
        </spirit:wire>
      </spirit:port>
      <spirit:port>
        <spirit:name>s_axis_eth_tx_tready</spirit:name>
        <spirit:wire>
          <spirit:direction>out</spirit:direction>
          <spirit:wireTypeDefs>
            <spirit:wireTypeDef>
              <spirit:typeName>std_logic</spirit:typeName>
              <spirit:viewNameRef>xilinx_anylanguagesynthesis</spirit:viewNameRef>
              <spirit:viewNameRef>xilinx_anylanguagebehavioralsimulation</spirit:viewNameRef>
            </spirit:wireTypeDef>
          </spirit:wireTypeDefs>
        </spirit:wire>
      </spirit:port>
      <spirit:port>
        <spirit:name>s_axis_eth_tx_tvalid</spirit:name>
        <spirit:wire>
          <spirit:direction>in</spirit:direction>
          <spirit:wireTypeDefs>
            <spirit:wireTypeDef>
              <spirit:typeName>std_logic</spirit:typeName>
              <spirit:viewNameRef>xilinx_anylanguagesynthesis</spirit:viewNameRef>
              <spirit:viewNameRef>xilinx_anylanguagebehavioralsimulation</spirit:viewNameRef>
            </spirit:wireTypeDef>
          </spirit:wireTypeDefs>
        </spirit:wire>
      </spirit:port>
    </spirit:ports>
  </spirit:model>
  <spirit:fileSets>
    <spirit:fileSet>
      <spirit:name>xilinx_anylanguagesynthesis_view_fileset</spirit:name>
      <spirit:file>
        <spirit:name>src/axi_ethernet_streamer_picoblaze_ethernet_lite_controller_0_0/axi_ethernet_streamer_picoblaze_ethernet_lite_controller_0_0.xci</spirit:name>
        <spirit:userFileType>xci</spirit:userFileType>
        <spirit:userFileType>IMPORTED_FILE</spirit:userFileType>
        <spirit:userFileType>CELL_NAME_u_pb</spirit:userFileType>
        <spirit:define>
          <spirit:name>processing_order</spirit:name>
          <spirit:value>early</spirit:value>
        </spirit:define>
      </spirit:file>
      <spirit:file>
        <spirit:name>src/axi_ethernet_streamer_axi_datamover_0_0/axi_ethernet_streamer_axi_datamover_0_0.xci</spirit:name>
        <spirit:userFileType>xci</spirit:userFileType>
        <spirit:userFileType>IMPORTED_FILE</spirit:userFileType>
        <spirit:userFileType>CELL_NAME_u_dm</spirit:userFileType>
        <spirit:define>
          <spirit:name>processing_order</spirit:name>
          <spirit:value>early</spirit:value>
        </spirit:define>
      </spirit:file>
      <spirit:file>
        <spirit:name>src/axi_ethernet_streamer_axi_protocol_converter_0_0/axi_ethernet_streamer_axi_protocol_converter_0_0.xci</spirit:name>
        <spirit:userFileType>xci</spirit:userFileType>
        <spirit:userFileType>IMPORTED_FILE</spirit:userFileType>
        <spirit:userFileType>CELL_NAME_u_conv</spirit:userFileType>
        <spirit:define>
          <spirit:name>processing_order</spirit:name>
          <spirit:value>early</spirit:value>
        </spirit:define>
      </spirit:file>
      <spirit:file>
        <spirit:name>src/axi_ethernet_streamer_axi_ethernetlite_0_0/axi_ethernet_streamer_axi_ethernetlite_0_0.xci</spirit:name>
        <spirit:userFileType>xci</spirit:userFileType>
        <spirit:userFileType>IMPORTED_FILE</spirit:userFileType>
        <spirit:userFileType>CELL_NAME_u_eth</spirit:userFileType>
        <spirit:define>
          <spirit:name>processing_order</spirit:name>
          <spirit:value>early</spirit:value>
        </spirit:define>
      </spirit:file>
      <spirit:file>
        <spirit:name>src/axi_ethernet_streamer_xlconstant_0_0/axi_ethernet_streamer_xlconstant_0_0.xci</spirit:name>
        <spirit:userFileType>xci</spirit:userFileType>
        <spirit:userFileType>IMPORTED_FILE</spirit:userFileType>
        <spirit:userFileType>CELL_NAME_tie</spirit:userFileType>
        <spirit:define>
          <spirit:name>processing_order</spirit:name>
          <spirit:value>early</spirit:value>
        </spirit:define>
      </spirit:file>
      <spirit:file>
        <spirit:name>src/axi_ethernet_streamer_rst_clk100_100M_0/axi_ethernet_streamer_rst_clk100_100M_0.xci</spirit:name>
        <spirit:userFileType>xci</spirit:userFileType>
        <spirit:userFileType>IMPORTED_FILE</spirit:userFileType>
        <spirit:userFileType>CELL_NAME_u_rst</spirit:userFileType>
        <spirit:define>
          <spirit:name>processing_order</spirit:name>
          <spirit:value>early</spirit:value>
        </spirit:define>
      </spirit:file>
      <spirit:file>
        <spirit:name>src/axi_ethernet_streamer_xbar_0/axi_ethernet_streamer_xbar_0.xci</spirit:name>
        <spirit:userFileType>xci</spirit:userFileType>
        <spirit:userFileType>IMPORTED_FILE</spirit:userFileType>
        <spirit:userFileType>CELL_NAME_u_xbar/xbar</spirit:userFileType>
        <spirit:define>
          <spirit:name>processing_order</spirit:name>
          <spirit:value>early</spirit:value>
        </spirit:define>
      </spirit:file>
      <spirit:file>
        <spirit:name>src/axi_ethernet_streamer_system_ila_0_0/axi_ethernet_streamer_system_ila_0_0.xci</spirit:name>
        <spirit:userFileType>xci</spirit:userFileType>
        <spirit:userFileType>IMPORTED_FILE</spirit:userFileType>
        <spirit:userFileType>CELL_NAME_system_ila_0</spirit:userFileType>
        <spirit:define>
          <spirit:name>processing_order</spirit:name>
          <spirit:value>early</spirit:value>
        </spirit:define>
      </spirit:file>
      <spirit:file>
        <spirit:name>src/axi_ethernet_streamer_ooc.xdc</spirit:name>
        <spirit:userFileType>xdc</spirit:userFileType>
        <spirit:userFileType>IMPORTED_FILE</spirit:userFileType>
        <spirit:userFileType>SCOPED_TO_REF_axi_ethernet_streamer</spirit:userFileType>
        <spirit:userFileType>USED_IN_implementation</spirit:userFileType>
        <spirit:userFileType>USED_IN_out_of_context</spirit:userFileType>
        <spirit:userFileType>USED_IN_synthesis</spirit:userFileType>
        <spirit:define>
          <spirit:name>processing_order</spirit:name>
          <spirit:value>early</spirit:value>
        </spirit:define>
      </spirit:file>
      <spirit:file>
        <spirit:name>src/axi_ethernet_streamer.hwdef</spirit:name>
        <spirit:userFileType>hwdef</spirit:userFileType>
        <spirit:userFileType>IMPORTED_FILE</spirit:userFileType>
        <spirit:userFileType>USED_IN_hw_handoff</spirit:userFileType>
        <spirit:define>
          <spirit:name>processing_order</spirit:name>
          <spirit:value>early</spirit:value>
        </spirit:define>
      </spirit:file>
      <spirit:file>
        <spirit:name>src/axi_ethernet_streamer.v</spirit:name>
        <spirit:fileType>verilogSource</spirit:fileType>
        <spirit:userFileType>CHECKSUM_e25a741c</spirit:userFileType>
        <spirit:userFileType>IMPORTED_FILE</spirit:userFileType>
        <spirit:define>
          <spirit:name>processing_order</spirit:name>
          <spirit:value>early</spirit:value>
        </spirit:define>
      </spirit:file>
    </spirit:fileSet>
    <spirit:fileSet>
      <spirit:name>xilinx_anylanguagesynthesis_ohio_state_edu_user_picoblaze_ethernet_lite_controller_1_0__ref_view_fileset</spirit:name>
      <spirit:vendorExtensions>
        <xilinx:subCoreRef>
          <xilinx:componentRef xsi:type="xilinx:componentRefType" xilinx:vendor="ohio-state.edu" xilinx:library="user" xilinx:name="picoblaze_ethernet_lite_controller" xilinx:version="1.0">
            <xilinx:mode xilinx:name="create_mode"/>
          </xilinx:componentRef>
        </xilinx:subCoreRef>
      </spirit:vendorExtensions>
    </spirit:fileSet>
    <spirit:fileSet>
      <spirit:name>xilinx_anylanguagesynthesis_xilinx_com_ip_axi_datamover_5_1__ref_view_fileset</spirit:name>
      <spirit:vendorExtensions>
        <xilinx:subCoreRef>
          <xilinx:componentRef xilinx:vendor="xilinx.com" xilinx:library="ip" xilinx:name="axi_datamover" xilinx:version="5.1">
            <xilinx:mode xilinx:name="create_mode"/>
          </xilinx:componentRef>
        </xilinx:subCoreRef>
      </spirit:vendorExtensions>
    </spirit:fileSet>
    <spirit:fileSet>
      <spirit:name>xilinx_anylanguagesynthesis_xilinx_com_ip_axi_protocol_converter_2_1__ref_view_fileset</spirit:name>
      <spirit:vendorExtensions>
        <xilinx:subCoreRef>
          <xilinx:componentRef xilinx:vendor="xilinx.com" xilinx:library="ip" xilinx:name="axi_protocol_converter" xilinx:version="2.1">
            <xilinx:mode xilinx:name="create_mode"/>
          </xilinx:componentRef>
        </xilinx:subCoreRef>
      </spirit:vendorExtensions>
    </spirit:fileSet>
    <spirit:fileSet>
      <spirit:name>xilinx_anylanguagesynthesis_xilinx_com_ip_axi_ethernetlite_3_0__ref_view_fileset</spirit:name>
      <spirit:vendorExtensions>
        <xilinx:subCoreRef>
          <xilinx:componentRef xilinx:vendor="xilinx.com" xilinx:library="ip" xilinx:name="axi_ethernetlite" xilinx:version="3.0">
            <xilinx:mode xilinx:name="create_mode"/>
          </xilinx:componentRef>
        </xilinx:subCoreRef>
      </spirit:vendorExtensions>
    </spirit:fileSet>
    <spirit:fileSet>
      <spirit:name>xilinx_anylanguagesynthesis_xilinx_com_ip_xlconstant_1_1__ref_view_fileset</spirit:name>
      <spirit:vendorExtensions>
        <xilinx:subCoreRef>
          <xilinx:componentRef xilinx:vendor="xilinx.com" xilinx:library="ip" xilinx:name="xlconstant" xilinx:version="1.1">
            <xilinx:mode xilinx:name="create_mode"/>
          </xilinx:componentRef>
        </xilinx:subCoreRef>
      </spirit:vendorExtensions>
    </spirit:fileSet>
    <spirit:fileSet>
      <spirit:name>xilinx_anylanguagesynthesis_xilinx_com_ip_proc_sys_reset_5_0__ref_view_fileset</spirit:name>
      <spirit:vendorExtensions>
        <xilinx:subCoreRef>
          <xilinx:componentRef xilinx:vendor="xilinx.com" xilinx:library="ip" xilinx:name="proc_sys_reset" xilinx:version="5.0">
            <xilinx:mode xilinx:name="create_mode"/>
          </xilinx:componentRef>
        </xilinx:subCoreRef>
      </spirit:vendorExtensions>
    </spirit:fileSet>
    <spirit:fileSet>
      <spirit:name>xilinx_anylanguagesynthesis_xilinx_com_ip_axi_crossbar_2_1__ref_view_fileset</spirit:name>
      <spirit:vendorExtensions>
        <xilinx:subCoreRef>
          <xilinx:componentRef xilinx:vendor="xilinx.com" xilinx:library="ip" xilinx:name="axi_crossbar" xilinx:version="2.1">
            <xilinx:mode xilinx:name="create_mode"/>
          </xilinx:componentRef>
        </xilinx:subCoreRef>
      </spirit:vendorExtensions>
    </spirit:fileSet>
    <spirit:fileSet>
      <spirit:name>xilinx_anylanguagesynthesis_xilinx_com_ip_system_ila_1_0__ref_view_fileset</spirit:name>
      <spirit:vendorExtensions>
        <xilinx:subCoreRef>
          <xilinx:componentRef xilinx:vendor="xilinx.com" xilinx:library="ip" xilinx:name="system_ila" xilinx:version="1.0">
            <xilinx:mode xilinx:name="create_mode"/>
          </xilinx:componentRef>
        </xilinx:subCoreRef>
      </spirit:vendorExtensions>
    </spirit:fileSet>
    <spirit:fileSet>
      <spirit:name>xilinx_anylanguagebehavioralsimulation_view_fileset</spirit:name>
      <spirit:file>
        <spirit:name>src/axi_ethernet_streamer_picoblaze_ethernet_lite_controller_0_0/axi_ethernet_streamer_picoblaze_ethernet_lite_controller_0_0.xci</spirit:name>
        <spirit:userFileType>xci</spirit:userFileType>
        <spirit:userFileType>IMPORTED_FILE</spirit:userFileType>
        <spirit:userFileType>CELL_NAME_u_pb</spirit:userFileType>
        <spirit:define>
          <spirit:name>processing_order</spirit:name>
          <spirit:value>early</spirit:value>
        </spirit:define>
      </spirit:file>
      <spirit:file>
        <spirit:name>src/axi_ethernet_streamer_axi_datamover_0_0/axi_ethernet_streamer_axi_datamover_0_0.xci</spirit:name>
        <spirit:userFileType>xci</spirit:userFileType>
        <spirit:userFileType>IMPORTED_FILE</spirit:userFileType>
        <spirit:userFileType>CELL_NAME_u_dm</spirit:userFileType>
        <spirit:define>
          <spirit:name>processing_order</spirit:name>
          <spirit:value>early</spirit:value>
        </spirit:define>
      </spirit:file>
      <spirit:file>
        <spirit:name>src/axi_ethernet_streamer_axi_protocol_converter_0_0/axi_ethernet_streamer_axi_protocol_converter_0_0.xci</spirit:name>
        <spirit:userFileType>xci</spirit:userFileType>
        <spirit:userFileType>IMPORTED_FILE</spirit:userFileType>
        <spirit:userFileType>CELL_NAME_u_conv</spirit:userFileType>
        <spirit:define>
          <spirit:name>processing_order</spirit:name>
          <spirit:value>early</spirit:value>
        </spirit:define>
      </spirit:file>
      <spirit:file>
        <spirit:name>src/axi_ethernet_streamer_axi_ethernetlite_0_0/axi_ethernet_streamer_axi_ethernetlite_0_0.xci</spirit:name>
        <spirit:userFileType>xci</spirit:userFileType>
        <spirit:userFileType>IMPORTED_FILE</spirit:userFileType>
        <spirit:userFileType>CELL_NAME_u_eth</spirit:userFileType>
        <spirit:define>
          <spirit:name>processing_order</spirit:name>
          <spirit:value>early</spirit:value>
        </spirit:define>
      </spirit:file>
      <spirit:file>
        <spirit:name>src/axi_ethernet_streamer_xlconstant_0_0/axi_ethernet_streamer_xlconstant_0_0.xci</spirit:name>
        <spirit:userFileType>xci</spirit:userFileType>
        <spirit:userFileType>IMPORTED_FILE</spirit:userFileType>
        <spirit:userFileType>CELL_NAME_tie</spirit:userFileType>
        <spirit:define>
          <spirit:name>processing_order</spirit:name>
          <spirit:value>early</spirit:value>
        </spirit:define>
      </spirit:file>
      <spirit:file>
        <spirit:name>src/axi_ethernet_streamer_rst_clk100_100M_0/axi_ethernet_streamer_rst_clk100_100M_0.xci</spirit:name>
        <spirit:userFileType>xci</spirit:userFileType>
        <spirit:userFileType>IMPORTED_FILE</spirit:userFileType>
        <spirit:userFileType>CELL_NAME_u_rst</spirit:userFileType>
        <spirit:define>
          <spirit:name>processing_order</spirit:name>
          <spirit:value>early</spirit:value>
        </spirit:define>
      </spirit:file>
      <spirit:file>
        <spirit:name>src/axi_ethernet_streamer_xbar_0/axi_ethernet_streamer_xbar_0.xci</spirit:name>
        <spirit:userFileType>xci</spirit:userFileType>
        <spirit:userFileType>IMPORTED_FILE</spirit:userFileType>
        <spirit:userFileType>CELL_NAME_u_xbar/xbar</spirit:userFileType>
        <spirit:define>
          <spirit:name>processing_order</spirit:name>
          <spirit:value>early</spirit:value>
        </spirit:define>
      </spirit:file>
      <spirit:file>
        <spirit:name>src/axi_ethernet_streamer_system_ila_0_0/axi_ethernet_streamer_system_ila_0_0.xci</spirit:name>
        <spirit:userFileType>xci</spirit:userFileType>
        <spirit:userFileType>IMPORTED_FILE</spirit:userFileType>
        <spirit:userFileType>CELL_NAME_system_ila_0</spirit:userFileType>
        <spirit:define>
          <spirit:name>processing_order</spirit:name>
          <spirit:value>early</spirit:value>
        </spirit:define>
      </spirit:file>
      <spirit:file>
        <spirit:name>src/axi_ethernet_streamer.hwdef</spirit:name>
        <spirit:userFileType>hwdef</spirit:userFileType>
        <spirit:userFileType>IMPORTED_FILE</spirit:userFileType>
        <spirit:define>
          <spirit:name>processing_order</spirit:name>
          <spirit:value>early</spirit:value>
        </spirit:define>
      </spirit:file>
      <spirit:file>
        <spirit:name>src/axi_ethernet_streamer.v</spirit:name>
        <spirit:fileType>verilogSource</spirit:fileType>
        <spirit:userFileType>IMPORTED_FILE</spirit:userFileType>
        <spirit:define>
          <spirit:name>processing_order</spirit:name>
          <spirit:value>early</spirit:value>
        </spirit:define>
      </spirit:file>
    </spirit:fileSet>
    <spirit:fileSet>
      <spirit:name>xilinx_anylanguagebehavioralsimulation_ohio_state_edu_user_picoblaze_ethernet_lite_controller_1_0__ref_view_fileset</spirit:name>
      <spirit:vendorExtensions>
        <xilinx:subCoreRef>
          <xilinx:componentRef xsi:type="xilinx:componentRefType" xilinx:vendor="ohio-state.edu" xilinx:library="user" xilinx:name="picoblaze_ethernet_lite_controller" xilinx:version="1.0">
            <xilinx:mode xilinx:name="create_mode"/>
          </xilinx:componentRef>
        </xilinx:subCoreRef>
      </spirit:vendorExtensions>
    </spirit:fileSet>
    <spirit:fileSet>
      <spirit:name>xilinx_anylanguagebehavioralsimulation_xilinx_com_ip_axi_datamover_5_1__ref_view_fileset</spirit:name>
      <spirit:vendorExtensions>
        <xilinx:subCoreRef>
          <xilinx:componentRef xilinx:vendor="xilinx.com" xilinx:library="ip" xilinx:name="axi_datamover" xilinx:version="5.1">
            <xilinx:mode xilinx:name="create_mode"/>
          </xilinx:componentRef>
        </xilinx:subCoreRef>
      </spirit:vendorExtensions>
    </spirit:fileSet>
    <spirit:fileSet>
      <spirit:name>xilinx_anylanguagebehavioralsimulation_xilinx_com_ip_axi_protocol_converter_2_1__ref_view_fileset</spirit:name>
      <spirit:vendorExtensions>
        <xilinx:subCoreRef>
          <xilinx:componentRef xilinx:vendor="xilinx.com" xilinx:library="ip" xilinx:name="axi_protocol_converter" xilinx:version="2.1">
            <xilinx:mode xilinx:name="create_mode"/>
          </xilinx:componentRef>
        </xilinx:subCoreRef>
      </spirit:vendorExtensions>
    </spirit:fileSet>
    <spirit:fileSet>
      <spirit:name>xilinx_anylanguagebehavioralsimulation_xilinx_com_ip_axi_ethernetlite_3_0__ref_view_fileset</spirit:name>
      <spirit:vendorExtensions>
        <xilinx:subCoreRef>
          <xilinx:componentRef xilinx:vendor="xilinx.com" xilinx:library="ip" xilinx:name="axi_ethernetlite" xilinx:version="3.0">
            <xilinx:mode xilinx:name="create_mode"/>
          </xilinx:componentRef>
        </xilinx:subCoreRef>
      </spirit:vendorExtensions>
    </spirit:fileSet>
    <spirit:fileSet>
      <spirit:name>xilinx_anylanguagebehavioralsimulation_xilinx_com_ip_xlconstant_1_1__ref_view_fileset</spirit:name>
      <spirit:vendorExtensions>
        <xilinx:subCoreRef>
          <xilinx:componentRef xilinx:vendor="xilinx.com" xilinx:library="ip" xilinx:name="xlconstant" xilinx:version="1.1">
            <xilinx:mode xilinx:name="create_mode"/>
          </xilinx:componentRef>
        </xilinx:subCoreRef>
      </spirit:vendorExtensions>
    </spirit:fileSet>
    <spirit:fileSet>
      <spirit:name>xilinx_anylanguagebehavioralsimulation_xilinx_com_ip_proc_sys_reset_5_0__ref_view_fileset</spirit:name>
      <spirit:vendorExtensions>
        <xilinx:subCoreRef>
          <xilinx:componentRef xilinx:vendor="xilinx.com" xilinx:library="ip" xilinx:name="proc_sys_reset" xilinx:version="5.0">
            <xilinx:mode xilinx:name="create_mode"/>
          </xilinx:componentRef>
        </xilinx:subCoreRef>
      </spirit:vendorExtensions>
    </spirit:fileSet>
    <spirit:fileSet>
      <spirit:name>xilinx_anylanguagebehavioralsimulation_xilinx_com_ip_axi_crossbar_2_1__ref_view_fileset</spirit:name>
      <spirit:vendorExtensions>
        <xilinx:subCoreRef>
          <xilinx:componentRef xilinx:vendor="xilinx.com" xilinx:library="ip" xilinx:name="axi_crossbar" xilinx:version="2.1">
            <xilinx:mode xilinx:name="create_mode"/>
          </xilinx:componentRef>
        </xilinx:subCoreRef>
      </spirit:vendorExtensions>
    </spirit:fileSet>
    <spirit:fileSet>
      <spirit:name>xilinx_anylanguagebehavioralsimulation_xilinx_com_ip_system_ila_1_0__ref_view_fileset</spirit:name>
      <spirit:vendorExtensions>
        <xilinx:subCoreRef>
          <xilinx:componentRef xilinx:vendor="xilinx.com" xilinx:library="ip" xilinx:name="system_ila" xilinx:version="1.0">
            <xilinx:mode xilinx:name="create_mode"/>
          </xilinx:componentRef>
        </xilinx:subCoreRef>
      </spirit:vendorExtensions>
    </spirit:fileSet>
    <spirit:fileSet>
      <spirit:name>xilinx_xpgui_view_fileset</spirit:name>
      <spirit:file>
        <spirit:name>xgui/axi_ethernet_streamer_v1_0.tcl</spirit:name>
        <spirit:fileType>tclSource</spirit:fileType>
        <spirit:userFileType>CHECKSUM_f92e9879</spirit:userFileType>
        <spirit:userFileType>XGUI_VERSION_2</spirit:userFileType>
      </spirit:file>
    </spirit:fileSet>
  </spirit:fileSets>
  <spirit:description>axi_ethernet_streamer_v1_0</spirit:description>
  <spirit:parameters>
    <spirit:parameter>
      <spirit:name>Component_Name</spirit:name>
      <spirit:value spirit:resolve="user" spirit:id="PARAM_VALUE.Component_Name" spirit:order="1">axi_ethernet_streamer_v1_0</spirit:value>
    </spirit:parameter>
  </spirit:parameters>
  <spirit:vendorExtensions>
    <xilinx:coreExtensions>
      <xilinx:supportedFamilies>
        <xilinx:family xilinx:lifeCycle="Production">artix7</xilinx:family>
      </xilinx:supportedFamilies>
      <xilinx:taxonomies>
        <xilinx:taxonomy>/UserIP</xilinx:taxonomy>
      </xilinx:taxonomies>
      <xilinx:displayName>axi_ethernet_streamer_v1_0</xilinx:displayName>
      <xilinx:definitionSource>IPI</xilinx:definitionSource>
      <xilinx:coreRevision>2</xilinx:coreRevision>
      <xilinx:coreCreationDateTime>2018-04-20T13:22:18Z</xilinx:coreCreationDateTime>
      <xilinx:tags>
        <xilinx:tag xilinx:name="ohio-state.edu:user:axi_ethernet_streamer:1.0_ARCHIVE_LOCATION">v:/osu_ip/axi_ethernet_streamer</xilinx:tag>
      </xilinx:tags>
      <xilinx:configElementInfos>
        <xilinx:configElementInfo xilinx:referenceId="BUSIFPARAM_VALUE.CLK.CLK100.FREQ_HZ" xilinx:valueSource="user"/>
        <xilinx:configElementInfo xilinx:referenceId="BUSIFPARAM_VALUE.M_AXIS_ETH_RX.HAS_TKEEP" xilinx:valueSource="user_prop"/>
        <xilinx:configElementInfo xilinx:referenceId="BUSIFPARAM_VALUE.M_AXIS_ETH_RX.HAS_TLAST" xilinx:valueSource="user_prop"/>
        <xilinx:configElementInfo xilinx:referenceId="BUSIFPARAM_VALUE.M_AXIS_ETH_RX.HAS_TREADY" xilinx:valueSource="user_prop"/>
        <xilinx:configElementInfo xilinx:referenceId="BUSIFPARAM_VALUE.M_AXIS_ETH_RX.HAS_TSTRB" xilinx:valueSource="constant_prop"/>
        <xilinx:configElementInfo xilinx:referenceId="BUSIFPARAM_VALUE.M_AXIS_ETH_RX.TDATA_NUM_BYTES" xilinx:valueSource="user_prop"/>
        <xilinx:configElementInfo xilinx:referenceId="BUSIFPARAM_VALUE.M_AXIS_ETH_RX.TDEST_WIDTH" xilinx:valueSource="constant_prop"/>
        <xilinx:configElementInfo xilinx:referenceId="BUSIFPARAM_VALUE.M_AXIS_ETH_RX.TID_WIDTH" xilinx:valueSource="constant_prop"/>
        <xilinx:configElementInfo xilinx:referenceId="BUSIFPARAM_VALUE.M_AXIS_ETH_RX.TUSER_WIDTH" xilinx:valueSource="constant_prop"/>
        <xilinx:configElementInfo xilinx:referenceId="BUSIFPARAM_VALUE.RST.RESET_OUT.POLARITY" xilinx:valueSource="constant_prop"/>
        <xilinx:configElementInfo xilinx:referenceId="BUSIFPARAM_VALUE.S_AXIS_ETH_TX.HAS_TKEEP" xilinx:valueSource="user"/>
        <xilinx:configElementInfo xilinx:referenceId="BUSIFPARAM_VALUE.S_AXIS_ETH_TX.HAS_TLAST" xilinx:valueSource="user"/>
        <xilinx:configElementInfo xilinx:referenceId="BUSIFPARAM_VALUE.S_AXIS_ETH_TX.HAS_TREADY" xilinx:valueSource="user"/>
        <xilinx:configElementInfo xilinx:referenceId="BUSIFPARAM_VALUE.S_AXIS_ETH_TX.HAS_TSTRB" xilinx:valueSource="user"/>
        <xilinx:configElementInfo xilinx:referenceId="BUSIFPARAM_VALUE.S_AXIS_ETH_TX.LAYERED_METADATA" xilinx:valueSource="user"/>
        <xilinx:configElementInfo xilinx:referenceId="BUSIFPARAM_VALUE.S_AXIS_ETH_TX.TDATA_NUM_BYTES" xilinx:valueSource="user"/>
        <xilinx:configElementInfo xilinx:referenceId="BUSIFPARAM_VALUE.S_AXIS_ETH_TX.TDEST_WIDTH" xilinx:valueSource="user"/>
        <xilinx:configElementInfo xilinx:referenceId="BUSIFPARAM_VALUE.S_AXIS_ETH_TX.TID_WIDTH" xilinx:valueSource="user"/>
        <xilinx:configElementInfo xilinx:referenceId="BUSIFPARAM_VALUE.S_AXIS_ETH_TX.TUSER_WIDTH" xilinx:valueSource="user"/>
      </xilinx:configElementInfos>
    </xilinx:coreExtensions>
    <xilinx:packagingInfo>
      <xilinx:xilinxVersion>2017.2</xilinx:xilinxVersion>
      <xilinx:checksum xilinx:scope="busInterfaces" xilinx:value="fdac9561"/>
      <xilinx:checksum xilinx:scope="fileGroups" xilinx:value="83b6f566"/>
      <xilinx:checksum xilinx:scope="ports" xilinx:value="44db63ac"/>
      <xilinx:checksum xilinx:scope="parameters" xilinx:value="3d6e329a"/>
    </xilinx:packagingInfo>
  </spirit:vendorExtensions>
</spirit:component>
